README.rst
setup.py
receita/__init__.py
receita/cli.py
receita/tools/__init__.py
receita/tools/build.py
receita/tools/client.py
receita/tools/get.py
receita/tools/runner.py
receita_tools.egg-info/PKG-INFO
receita_tools.egg-info/SOURCES.txt
receita_tools.egg-info/dependency_links.txt
receita_tools.egg-info/entry_points.txt
receita_tools.egg-info/requires.txt
receita_tools.egg-info/top_level.txt