Metadata-Version: 1.1
Name: receita-tools
Version: 2.0.2
Summary: Tools to manipulate Receita's company data.
Home-page: http://github.com/vkruoso/receita-tools
Author: Vinicius K. Ruoso
Author-email: vinicius.ruoso@gmail.com
License: MIT License
Platform: any
Classifier: Programming Language :: Python
Classifier: Development Status :: 4 - Beta
Classifier: Natural Language :: English
Classifier: Environment :: Web Environment
Classifier: Intended Audience :: Developers
Classifier: Intended Audience :: End Users/Desktop
Classifier: License :: OSI Approved :: MIT License
Classifier: Operating System :: OS Independent
Classifier: Topic :: Utilities
Classifier: Topic :: Software Development :: Build Tools
Classifier: Topic :: Software Development :: Libraries :: Python Modules
